django_mailupy/__init__.py
django_mailupy/admin.py
django_mailupy/apps.py
django_mailupy/client.py
django_mailupy/models.py
django_mailupy/serializers.py
django_mailupy/urls.py
django_mailupy/viewsets.py
django_mailupy/migrations/0001_initial.py
django_mailupy/migrations/__init__.py
django_mailupy-0.1.0.dist-info/LICENSE
django_mailupy-0.1.0.dist-info/METADATA
django_mailupy-0.1.0.dist-info/WHEEL
django_mailupy-0.1.0.dist-info/top_level.txt
django_mailupy-0.1.0.dist-info/RECORD
