Metadata-Version: 2.1
Name: django-mailupy
Version: 0.1.0
Summary: Django app wrapping the MailUp Python client
Home-page: https://github.com/lotrekagency/django-mailupy
Author: Lotrèk
Author-email: Your Name <you@example.com>
License: MIT
Requires-Python: >=3.8
License-File: LICENSE
Requires-Dist: Django>=4.2
Requires-Dist: mailupy>=1.1.4
Provides-Extra: dev
Requires-Dist: pytest>=8.0; extra == "dev"
Requires-Dist: pytest-django>=4.8; extra == "dev"
Requires-Dist: pytest-cov>=5.0; extra == "dev"
Requires-Dist: model-bakery>=1.15; extra == "dev"
Provides-Extra: drf
Requires-Dist: djangorestframework>=3.12; extra == "drf"
